ezRL/__init__.py
ezRL/test.py
unrec/__init__.py
unrec/test.py
unrec-0.1.0.dist-info/METADATA
unrec-0.1.0.dist-info/WHEEL
unrec-0.1.0.dist-info/top_level.txt
unrec-0.1.0.dist-info/RECORD
