Metadata-Version: 2.1
Name: unrec
Version: 0.1.0
Summary: This is a tool to fix recursive calls to loop in a fully automatic manner.
Home-page: https://github.co.jp/
Author: TTLab
Author-email: t.tools.lab@gmail.com
License: CC0 v1.0
Platform: UNKNOWN
Classifier: Programming Language :: Python :: 3
Classifier: Topic :: Software Development :: Libraries
Classifier: License :: CC0 1.0 Universal (CC0 1.0) Public Domain Dedication
Requires-Dist: relpath
